buildarr_radarr/__init__.py
buildarr_radarr/api.py
buildarr_radarr/cli.py
buildarr_radarr/config/__init__.py
buildarr_radarr/config/settings/__init__.py
buildarr_radarr/config/settings/custom_formats/__init__.py
buildarr_radarr/config/settings/custom_formats/conditions/__init__.py
buildarr_radarr/config/settings/custom_formats/conditions/base.py
buildarr_radarr/config/settings/custom_formats/conditions/edition.py
buildarr_radarr/config/settings/custom_formats/conditions/indexer_flag.py
buildarr_radarr/config/settings/custom_formats/conditions/language.py
buildarr_radarr/config/settings/custom_formats/conditions/quality_modifier.py
buildarr_radarr/config/settings/custom_formats/conditions/release_group.py
buildarr_radarr/config/settings/custom_formats/conditions/release_title.py
buildarr_radarr/config/settings/custom_formats/conditions/resolution.py
buildarr_radarr/config/settings/custom_formats/conditions/size.py
buildarr_radarr/config/settings/custom_formats/conditions/source.py
buildarr_radarr/config/settings/custom_formats/custom_format.py
buildarr_radarr/config/settings/download_clients/__init__.py
buildarr_radarr/config/settings/download_clients/base.py
buildarr_radarr/config/settings/download_clients/torrent/__init__.py
buildarr_radarr/config/settings/download_clients/torrent/aria2.py
buildarr_radarr/config/settings/download_clients/torrent/base.py
buildarr_radarr/config/settings/download_clients/torrent/blackhole.py
buildarr_radarr/config/settings/download_clients/torrent/deluge.py
buildarr_radarr/config/settings/download_clients/torrent/downloadstation.py
buildarr_radarr/config/settings/download_clients/torrent/flood.py
buildarr_radarr/config/settings/download_clients/torrent/freebox.py
buildarr_radarr/config/settings/download_clients/torrent/hadouken.py
buildarr_radarr/config/settings/download_clients/torrent/qbittorrent.py
buildarr_radarr/config/settings/download_clients/torrent/rtorrent.py
buildarr_radarr-0.2.6.dist-info/LICENSE
buildarr_radarr-0.2.6.dist-info/METADATA
buildarr_radarr-0.2.6.dist-info/WHEEL
buildarr_radarr-0.2.6.dist-info/entry_points.txt
buildarr_radarr-0.2.6.dist-info/RECORD
